[{"date":"03-06-2020","death":0,"hospitalizations":269},{"date":"03-07-2020","death":0,"hospitalizations":269},{"date":"03-08-2020","death":0,"hospitalizations":269},{"date":"03-09-2020","death":0,"hospitalizations":269},{"date":"03-10-2020","death":0,"hospitalizations":270},{"date":"03-11-2020","death":0,"hospitalizations":270},{"date":"03-12-2020","death":0,"hospitalizations":270},{"date":"03-13-2020","death":0,"hospitalizations":270},{"date":"03-14-2020","death":0,"hospitalizations":271},{"date":"03-15-2020","death":0,"hospitalizations":271},{"date":"03-16-2020","death":0,"hospitalizations":272},{"date":"03-17-2020","death":0,"hospitalizations":273},{"date":"03-18-2020","death":0,"hospitalizations":275},{"date":"03-19-2020","death":0,"hospitalizations":277},{"date":"03-20-2020","death":0,"hospitalizations":280},{"date":"03-21-2020","death":0,"hospitalizations":284},{"date":"03-22-2020","death":0,"hospitalizations":289},{"date":"03-23-2020","death":0,"hospitalizations":296},{"date":"03-24-2020","death":0,"hospitalizations":305},{"date":"03-25-2020","death":0,"hospitalizations":316},{"date":"03-26-2020","death":2,"hospitalizations":332},{"date":"03-27-2020","death":4,"hospitalizations":350},{"date":"03-28-2020","death":6,"hospitalizations":374},{"date":"03-29-2020","death":9,"hospitalizations":401},{"date":"03-30-2020","death":14,"hospitalizations":434},{"date":"03-31-2020","death":19,"hospitalizations":472},{"date":"04-01-2020","death":25,"hospitalizations":514},{"date":"04-02-2020","death":32,"hospitalizations":560},{"date":"04-03-2020","death":41,"hospitalizations":609},{"date":"04-04-2020","death":51,"hospitalizations":659},{"date":"04-05-2020","death":63,"hospitalizations":709},{"date":"04-06-2020","death":76,"hospitalizations":756},{"date":"04-07-2020","death":91,"hospitalizations":801},{"date":"04-08-2020","death":106,"hospitalizations":843},{"date":"04-09-2020","death":123,"hospitalizations":882},{"date":"04-10-2020","death":142,"hospitalizations":918},{"date":"04-11-2020","death":161,"hospitalizations":951},{"date":"04-12-2020","death":181,"hospitalizations":983},{"date":"04-13-2020","death":202,"hospitalizations":1012},{"date":"04-14-2020","death":224,"hospitalizations":1040},{"date":"04-15-2020","death":247,"hospitalizations":1066},{"date":"04-16-2020","death":270,"hospitalizations":1092},{"date":"04-17-2020","death":295,"hospitalizations":1116},{"date":"04-18-2020","death":320,"hospitalizations":1139},{"date":"04-19-2020","death":346,"hospitalizations":1161},{"date":"04-20-2020","death":372,"hospitalizations":1182},{"date":"04-21-2020","death":399,"hospitalizations":1203},{"date":"04-22-2020","death":427,"hospitalizations":1224},{"date":"04-23-2020","death":456,"hospitalizations":1243},{"date":"04-24-2020","death":485,"hospitalizations":1262},{"date":"04-25-2020","death":515,"hospitalizations":1280},{"date":"04-26-2020","death":545,"hospitalizations":1297},{"date":"04-27-2020","death":576,"hospitalizations":1314},{"date":"04-28-2020","death":607,"hospitalizations":1329},{"date":"04-29-2020","death":639,"hospitalizations":1342},{"date":"04-30-2020","death":671,"hospitalizations":1355},{"date":"05-01-2020","death":703,"hospitalizations":1366},{"date":"05-02-2020","death":736,"hospitalizations":1376},{"date":"05-03-2020","death":770,"hospitalizations":1384},{"date":"05-04-2020","death":803,"hospitalizations":1391},{"date":"05-05-2020","death":837,"hospitalizations":1396},{"date":"05-06-2020","death":871,"hospitalizations":1400},{"date":"05-07-2020","death":905,"hospitalizations":1402},{"date":"05-08-2020","death":939,"hospitalizations":1403},{"date":"05-09-2020","death":973,"hospitalizations":1403},{"date":"05-10-2020","death":1007,"hospitalizations":1402},{"date":"05-11-2020","death":1042,"hospitalizations":1400},{"date":"05-12-2020","death":1076,"hospitalizations":1397},{"date":"05-13-2020","death":1110,"hospitalizations":1393},{"date":"05-14-2020","death":1144,"hospitalizations":1388},{"date":"05-15-2020","death":1178,"hospitalizations":1383},{"date":"05-16-2020","death":1211,"hospitalizations":1378},{"date":"05-17-2020","death":1245,"hospitalizations":1372},{"date":"05-18-2020","death":1278,"hospitalizations":1365},{"date":"05-19-2020","death":1312,"hospitalizations":1358},{"date":"05-20-2020","death":1345,"hospitalizations":1351},{"date":"05-21-2020","death":1378,"hospitalizations":1343},{"date":"05-22-2020","death":1410,"hospitalizations":1336},{"date":"05-23-2020","death":1443,"hospitalizations":1327},{"date":"05-24-2020","death":1475,"hospitalizations":1319},{"date":"05-25-2020","death":1507,"hospitalizations":1310},{"date":"05-26-2020","death":1539,"hospitalizations":1302},{"date":"05-27-2020","death":1570,"hospitalizations":1293},{"date":"05-28-2020","death":1601,"hospitalizations":1284},{"date":"05-29-2020","death":1632,"hospitalizations":1274},{"date":"05-30-2020","death":1663,"hospitalizations":1265},{"date":"05-31-2020","death":1693,"hospitalizations":1255},{"date":"06-01-2020","death":1724,"hospitalizations":1246},{"date":"06-02-2020","death":1753,"hospitalizations":1236},{"date":"06-03-2020","death":1783,"hospitalizations":1226},{"date":"06-04-2020","death":1812,"hospitalizations":1216},{"date":"06-05-2020","death":1841,"hospitalizations":1206},{"date":"06-06-2020","death":1870,"hospitalizations":1196},{"date":"06-07-2020","death":1898,"hospitalizations":1186},{"date":"06-08-2020","death":1926,"hospitalizations":1176},{"date":"06-09-2020","death":1954,"hospitalizations":1166},{"date":"06-10-2020","death":1982,"hospitalizations":1156},{"date":"06-11-2020","death":2009,"hospitalizations":1146},{"date":"06-12-2020","death":2036,"hospitalizations":1136},{"date":"06-13-2020","death":2062,"hospitalizations":1126},{"date":"06-14-2020","death":2089,"hospitalizations":1115},{"date":"06-15-2020","death":2115,"hospitalizations":1105},{"date":"06-16-2020","death":2140,"hospitalizations":1095},{"date":"06-17-2020","death":2166,"hospitalizations":1085},{"date":"06-18-2020","death":2191,"hospitalizations":1075},{"date":"06-19-2020","death":2215,"hospitalizations":1065},{"date":"06-20-2020","death":2240,"hospitalizations":1055},{"date":"06-21-2020","death":2264,"hospitalizations":1045},{"date":"06-22-2020","death":2288,"hospitalizations":1035},{"date":"06-23-2020","death":2311,"hospitalizations":1025},{"date":"06-24-2020","death":2334,"hospitalizations":1015},{"date":"06-25-2020","death":2357,"hospitalizations":1005},{"date":"06-26-2020","death":2380,"hospitalizations":995},{"date":"06-27-2020","death":2402,"hospitalizations":985},{"date":"06-28-2020","death":2424,"hospitalizations":975},{"date":"06-29-2020","death":2446,"hospitalizations":965},{"date":"06-30-2020","death":2467,"hospitalizations":956},{"date":"07-01-2020","death":2489,"hospitalizations":946},{"date":"07-02-2020","death":2509,"hospitalizations":937},{"date":"07-03-2020","death":2530,"hospitalizations":927},{"date":"07-04-2020","death":2550,"hospitalizations":918},{"date":"07-05-2020","death":2570,"hospitalizations":908},{"date":"07-06-2020","death":2590,"hospitalizations":899},{"date":"07-07-2020","death":2609,"hospitalizations":890},{"date":"07-08-2020","death":2629,"hospitalizations":881},{"date":"07-09-2020","death":2647,"hospitalizations":872},{"date":"07-10-2020","death":2666,"hospitalizations":863},{"date":"07-11-2020","death":2684,"hospitalizations":854},{"date":"07-12-2020","death":2703,"hospitalizations":845},{"date":"07-13-2020","death":2720,"hospitalizations":836},{"date":"07-14-2020","death":2738,"hospitalizations":828},{"date":"07-15-2020","death":2755,"hospitalizations":819},{"date":"07-16-2020","death":2772,"hospitalizations":811},{"date":"07-17-2020","death":2788,"hospitalizations":802},{"date":"07-18-2020","death":2804,"hospitalizations":794},{"date":"07-19-2020","death":2820,"hospitalizations":786},{"date":"07-20-2020","death":2836,"hospitalizations":778},{"date":"07-21-2020","death":2852,"hospitalizations":770},{"date":"07-22-2020","death":2868,"hospitalizations":762},{"date":"07-23-2020","death":2883,"hospitalizations":755},{"date":"07-24-2020","death":2898,"hospitalizations":749},{"date":"07-25-2020","death":2913,"hospitalizations":743},{"date":"07-26-2020","death":2927,"hospitalizations":739},{"date":"07-27-2020","death":2942,"hospitalizations":737},{"date":"07-28-2020","death":2956,"hospitalizations":736},{"date":"07-29-2020","death":2971,"hospitalizations":736},{"date":"07-30-2020","death":2985,"hospitalizations":738},{"date":"07-31-2020","death":3000,"hospitalizations":743},{"date":"08-01-2020","death":3015,"hospitalizations":749},{"date":"08-02-2020","death":3029,"hospitalizations":758},{"date":"08-03-2020","death":3044,"hospitalizations":769},{"date":"08-04-2020","death":3060,"hospitalizations":783},{"date":"08-05-2020","death":3076,"hospitalizations":799},{"date":"08-06-2020","death":3092,"hospitalizations":818},{"date":"08-07-2020","death":3109,"hospitalizations":840},{"date":"08-08-2020","death":3127,"hospitalizations":864},{"date":"08-09-2020","death":3145,"hospitalizations":891},{"date":"08-10-2020","death":3164,"hospitalizations":920},{"date":"08-11-2020","death":3184,"hospitalizations":951},{"date":"08-12-2020","death":3205,"hospitalizations":985},{"date":"08-13-2020","death":3226,"hospitalizations":1022},{"date":"08-14-2020","death":3249,"hospitalizations":1061},{"date":"08-15-2020","death":3274,"hospitalizations":1103},{"date":"08-16-2020","death":3299,"hospitalizations":1147},{"date":"08-17-2020","death":3325,"hospitalizations":1193},{"date":"08-18-2020","death":3354,"hospitalizations":1243},{"date":"08-19-2020","death":3383,"hospitalizations":1295},{"date":"08-20-2020","death":3414,"hospitalizations":1349},{"date":"08-21-2020","death":3447,"hospitalizations":1407},{"date":"08-22-2020","death":3481,"hospitalizations":1467},{"date":"08-23-2020","death":3517,"hospitalizations":1530},{"date":"08-24-2020","death":3555,"hospitalizations":1596},{"date":"08-25-2020","death":3595,"hospitalizations":1666},{"date":"08-26-2020","death":3637,"hospitalizations":1738},{"date":"08-27-2020","death":3681,"hospitalizations":1813},{"date":"08-28-2020","death":3728,"hospitalizations":1891},{"date":"08-29-2020","death":3777,"hospitalizations":1973},{"date":"08-30-2020","death":3828,"hospitalizations":2057},{"date":"08-31-2020","death":3882,"hospitalizations":2145},{"date":"09-01-2020","death":3938,"hospitalizations":2236},{"date":"09-02-2020","death":3997,"hospitalizations":2330},{"date":"09-03-2020","death":4059,"hospitalizations":2426},{"date":"09-04-2020","death":4124,"hospitalizations":2526},{"date":"09-05-2020","death":4192,"hospitalizations":2629},{"date":"09-06-2020","death":4263,"hospitalizations":2734},{"date":"09-07-2020","death":4338,"hospitalizations":2843},{"date":"09-08-2020","death":4436,"hospitalizations":2971},{"date":"09-09-2020","death":4541,"hospitalizations":3101},{"date":"09-10-2020","death":4650,"hospitalizations":3233},{"date":"09-11-2020","death":4765,"hospitalizations":3368},{"date":"09-12-2020","death":4885,"hospitalizations":3503},{"date":"09-13-2020","death":5011,"hospitalizations":3641},{"date":"09-14-2020","death":5142,"hospitalizations":3779},{"date":"09-15-2020","death":5279,"hospitalizations":3918},{"date":"09-16-2020","death":5421,"hospitalizations":4058},{"date":"09-17-2020","death":5568,"hospitalizations":4197},{"date":"09-18-2020","death":5721,"hospitalizations":4336},{"date":"09-19-2020","death":5880,"hospitalizations":4474},{"date":"09-20-2020","death":6044,"hospitalizations":4611},{"date":"09-21-2020","death":6214,"hospitalizations":4746},{"date":"09-22-2020","death":6389,"hospitalizations":4879},{"date":"09-23-2020","death":6569,"hospitalizations":5009},{"date":"09-24-2020","death":6755,"hospitalizations":5136},{"date":"09-25-2020","death":6945,"hospitalizations":5259},{"date":"09-26-2020","death":7141,"hospitalizations":5379},{"date":"09-27-2020","death":7341,"hospitalizations":5493},{"date":"09-28-2020","death":7546,"hospitalizations":5603},{"date":"09-29-2020","death":7755,"hospitalizations":5706},{"date":"09-30-2020","death":7969,"hospitalizations":5804},{"date":"10-01-2020","death":8186,"hospitalizations":5895},{"date":"10-02-2020","death":8407,"hospitalizations":5979},{"date":"10-03-2020","death":8632,"hospitalizations":6056},{"date":"10-04-2020","death":8860,"hospitalizations":6126},{"date":"10-05-2020","death":9090,"hospitalizations":6187},{"date":"10-06-2020","death":9323,"hospitalizations":6241},{"date":"10-07-2020","death":9559,"hospitalizations":6285},{"date":"10-08-2020","death":9796,"hospitalizations":6322},{"date":"10-09-2020","death":10035,"hospitalizations":6350},{"date":"10-10-2020","death":10275,"hospitalizations":6369},{"date":"10-11-2020","death":10516,"hospitalizations":6379},{"date":"10-12-2020","death":10758,"hospitalizations":6381},{"date":"10-13-2020","death":11000,"hospitalizations":6374},{"date":"10-14-2020","death":11242,"hospitalizations":6359},{"date":"10-15-2020","death":11484,"hospitalizations":6336},{"date":"10-16-2020","death":11725,"hospitalizations":6304},{"date":"10-17-2020","death":11964,"hospitalizations":6264},{"date":"10-18-2020","death":12203,"hospitalizations":6217}]