[{"date":"03-06-2020","hospitalizations":0,"death":0},{"date":"03-07-2020","hospitalizations":0,"death":0},{"date":"03-08-2020","hospitalizations":0,"death":0},{"date":"03-09-2020","hospitalizations":0,"death":0},{"date":"03-10-2020","hospitalizations":0,"death":0},{"date":"03-11-2020","hospitalizations":0,"death":0},{"date":"03-12-2020","hospitalizations":0,"death":0},{"date":"03-13-2020","hospitalizations":1,"death":0},{"date":"03-14-2020","hospitalizations":1,"death":0},{"date":"03-15-2020","hospitalizations":2,"death":0},{"date":"03-16-2020","hospitalizations":2,"death":0},{"date":"03-17-2020","hospitalizations":3,"death":0},{"date":"03-18-2020","hospitalizations":5,"death":0},{"date":"03-19-2020","hospitalizations":7,"death":0},{"date":"03-20-2020","hospitalizations":9,"death":0},{"date":"03-21-2020","hospitalizations":13,"death":0},{"date":"03-22-2020","hospitalizations":17,"death":0},{"date":"03-23-2020","hospitalizations":23,"death":0},{"date":"03-24-2020","hospitalizations":29,"death":0},{"date":"03-25-2020","hospitalizations":37,"death":0},{"date":"03-26-2020","hospitalizations":47,"death":0},{"date":"03-27-2020","hospitalizations":58,"death":0},{"date":"03-28-2020","hospitalizations":70,"death":0},{"date":"03-29-2020","hospitalizations":82,"death":0},{"date":"03-30-2020","hospitalizations":96,"death":0},{"date":"03-31-2020","hospitalizations":110,"death":0},{"date":"04-01-2020","hospitalizations":123,"death":0},{"date":"04-02-2020","hospitalizations":136,"death":0},{"date":"04-03-2020","hospitalizations":147,"death":0},{"date":"04-04-2020","hospitalizations":158,"death":0},{"date":"04-05-2020","hospitalizations":167,"death":0},{"date":"04-06-2020","hospitalizations":175,"death":0},{"date":"04-07-2020","hospitalizations":183,"death":0},{"date":"04-08-2020","hospitalizations":189,"death":0},{"date":"04-09-2020","hospitalizations":196,"death":0},{"date":"04-10-2020","hospitalizations":201,"death":0},{"date":"04-11-2020","hospitalizations":206,"death":0},{"date":"04-12-2020","hospitalizations":210,"death":0},{"date":"04-13-2020","hospitalizations":215,"death":0},{"date":"04-14-2020","hospitalizations":218,"death":0},{"date":"04-15-2020","hospitalizations":222,"death":0},{"date":"04-16-2020","hospitalizations":225,"death":0},{"date":"04-17-2020","hospitalizations":228,"death":0},{"date":"04-18-2020","hospitalizations":230,"death":0},{"date":"04-19-2020","hospitalizations":233,"death":0},{"date":"04-20-2020","hospitalizations":235,"death":0},{"date":"04-21-2020","hospitalizations":238,"death":0},{"date":"04-22-2020","hospitalizations":240,"death":0},{"date":"04-23-2020","hospitalizations":242,"death":0},{"date":"04-24-2020","hospitalizations":244,"death":0},{"date":"04-25-2020","hospitalizations":246,"death":5},{"date":"04-26-2020","hospitalizations":247,"death":11},{"date":"04-27-2020","hospitalizations":249,"death":18},{"date":"04-28-2020","hospitalizations":251,"death":24},{"date":"04-29-2020","hospitalizations":253,"death":31},{"date":"04-30-2020","hospitalizations":254,"death":37},{"date":"05-01-2020","hospitalizations":256,"death":44},{"date":"05-02-2020","hospitalizations":257,"death":50},{"date":"05-03-2020","hospitalizations":259,"death":57},{"date":"05-04-2020","hospitalizations":260,"death":63},{"date":"05-05-2020","hospitalizations":262,"death":70},{"date":"05-06-2020","hospitalizations":263,"death":77},{"date":"05-07-2020","hospitalizations":265,"death":84},{"date":"05-08-2020","hospitalizations":267,"death":90},{"date":"05-09-2020","hospitalizations":269,"death":97},{"date":"05-10-2020","hospitalizations":271,"death":104},{"date":"05-11-2020","hospitalizations":273,"death":111},{"date":"05-12-2020","hospitalizations":275,"death":118},{"date":"05-13-2020","hospitalizations":278,"death":125},{"date":"05-14-2020","hospitalizations":280,"death":133},{"date":"05-15-2020","hospitalizations":283,"death":140},{"date":"05-16-2020","hospitalizations":286,"death":147},{"date":"05-17-2020","hospitalizations":289,"death":155},{"date":"05-18-2020","hospitalizations":293,"death":162},{"date":"05-19-2020","hospitalizations":296,"death":170},{"date":"05-20-2020","hospitalizations":300,"death":177},{"date":"05-21-2020","hospitalizations":304,"death":185},{"date":"05-22-2020","hospitalizations":308,"death":193},{"date":"05-23-2020","hospitalizations":312,"death":201},{"date":"05-24-2020","hospitalizations":316,"death":209},{"date":"05-25-2020","hospitalizations":320,"death":217},{"date":"05-26-2020","hospitalizations":325,"death":225},{"date":"05-27-2020","hospitalizations":329,"death":234},{"date":"05-28-2020","hospitalizations":334,"death":242},{"date":"05-29-2020","hospitalizations":338,"death":251},{"date":"05-30-2020","hospitalizations":343,"death":259},{"date":"05-31-2020","hospitalizations":348,"death":268},{"date":"06-01-2020","hospitalizations":353,"death":277},{"date":"06-02-2020","hospitalizations":358,"death":286},{"date":"06-03-2020","hospitalizations":363,"death":295},{"date":"06-04-2020","hospitalizations":368,"death":305},{"date":"06-05-2020","hospitalizations":373,"death":314},{"date":"06-06-2020","hospitalizations":378,"death":324},{"date":"06-07-2020","hospitalizations":383,"death":334},{"date":"06-08-2020","hospitalizations":389,"death":343},{"date":"06-09-2020","hospitalizations":394,"death":353},{"date":"06-10-2020","hospitalizations":399,"death":364},{"date":"06-11-2020","hospitalizations":405,"death":374},{"date":"06-12-2020","hospitalizations":410,"death":384},{"date":"06-13-2020","hospitalizations":416,"death":395},{"date":"06-14-2020","hospitalizations":422,"death":406},{"date":"06-15-2020","hospitalizations":427,"death":416},{"date":"06-16-2020","hospitalizations":433,"death":428},{"date":"06-17-2020","hospitalizations":439,"death":439},{"date":"06-18-2020","hospitalizations":445,"death":450},{"date":"06-19-2020","hospitalizations":450,"death":461},{"date":"06-20-2020","hospitalizations":456,"death":473},{"date":"06-21-2020","hospitalizations":462,"death":485},{"date":"06-22-2020","hospitalizations":468,"death":497},{"date":"06-23-2020","hospitalizations":474,"death":509},{"date":"06-24-2020","hospitalizations":480,"death":521},{"date":"06-25-2020","hospitalizations":487,"death":533},{"date":"06-26-2020","hospitalizations":493,"death":546},{"date":"06-27-2020","hospitalizations":499,"death":559},{"date":"06-28-2020","hospitalizations":505,"death":572},{"date":"06-29-2020","hospitalizations":511,"death":585},{"date":"06-30-2020","hospitalizations":518,"death":598},{"date":"07-01-2020","hospitalizations":524,"death":611},{"date":"07-02-2020","hospitalizations":531,"death":625},{"date":"07-03-2020","hospitalizations":538,"death":638},{"date":"07-04-2020","hospitalizations":547,"death":652},{"date":"07-05-2020","hospitalizations":558,"death":666},{"date":"07-06-2020","hospitalizations":572,"death":681},{"date":"07-07-2020","hospitalizations":590,"death":695},{"date":"07-08-2020","hospitalizations":612,"death":711},{"date":"07-09-2020","hospitalizations":640,"death":727},{"date":"07-10-2020","hospitalizations":675,"death":743},{"date":"07-11-2020","hospitalizations":718,"death":761},{"date":"07-12-2020","hospitalizations":770,"death":780},{"date":"07-13-2020","hospitalizations":834,"death":800},{"date":"07-14-2020","hospitalizations":912,"death":821},{"date":"07-15-2020","hospitalizations":1007,"death":845},{"date":"07-16-2020","hospitalizations":1122,"death":872},{"date":"07-17-2020","hospitalizations":1259,"death":901},{"date":"07-18-2020","hospitalizations":1422,"death":934},{"date":"07-19-2020","hospitalizations":1613,"death":971},{"date":"07-20-2020","hospitalizations":1836,"death":1013},{"date":"07-21-2020","hospitalizations":2095,"death":1061},{"date":"07-22-2020","hospitalizations":2403,"death":1126},{"date":"07-23-2020","hospitalizations":2760,"death":1206},{"date":"07-24-2020","hospitalizations":3167,"death":1299},{"date":"07-25-2020","hospitalizations":3629,"death":1405},{"date":"07-26-2020","hospitalizations":4150,"death":1526},{"date":"07-27-2020","hospitalizations":4735,"death":1665},{"date":"07-28-2020","hospitalizations":5388,"death":1823},{"date":"07-29-2020","hospitalizations":6113,"death":2003},{"date":"07-30-2020","hospitalizations":6913,"death":2207},{"date":"07-31-2020","hospitalizations":7788,"death":2438},{"date":"08-01-2020","hospitalizations":8738,"death":2697},{"date":"08-02-2020","hospitalizations":9759,"death":2987},{"date":"08-03-2020","hospitalizations":10848,"death":3311},{"date":"08-04-2020","hospitalizations":11994,"death":3671},{"date":"08-05-2020","hospitalizations":13188,"death":4068},{"date":"08-06-2020","hospitalizations":14415,"death":4504},{"date":"08-07-2020","hospitalizations":15646,"death":4980},{"date":"08-08-2020","hospitalizations":16904,"death":5496},{"date":"08-09-2020","hospitalizations":18124,"death":6052},{"date":"08-10-2020","hospitalizations":19295,"death":6648},{"date":"08-11-2020","hospitalizations":20398,"death":7282},{"date":"08-12-2020","hospitalizations":21413,"death":7951},{"date":"08-13-2020","hospitalizations":22321,"death":8653},{"date":"08-14-2020","hospitalizations":23106,"death":9384},{"date":"08-15-2020","hospitalizations":23756,"death":10142},{"date":"08-16-2020","hospitalizations":24260,"death":10920},{"date":"08-17-2020","hospitalizations":24612,"death":11716},{"date":"08-18-2020","hospitalizations":24810,"death":12523},{"date":"08-19-2020","hospitalizations":24860,"death":13335},{"date":"08-20-2020","hospitalizations":24758,"death":14155},{"date":"08-21-2020","hospitalizations":24522,"death":14970},{"date":"08-22-2020","hospitalizations":24160,"death":15779},{"date":"08-23-2020","hospitalizations":23684,"death":16577},{"date":"08-24-2020","hospitalizations":23112,"death":17362},{"date":"08-25-2020","hospitalizations":22449,"death":18130},{"date":"08-26-2020","hospitalizations":21715,"death":18879},{"date":"08-27-2020","hospitalizations":20923,"death":19606},{"date":"08-28-2020","hospitalizations":20086,"death":20309},{"date":"08-29-2020","hospitalizations":19217,"death":20986},{"date":"08-30-2020","hospitalizations":18337,"death":21636},{"date":"08-31-2020","hospitalizations":17431,"death":22260},{"date":"09-01-2020","hospitalizations":16532,"death":22855},{"date":"09-02-2020","hospitalizations":15642,"death":23422},{"date":"09-03-2020","hospitalizations":14766,"death":23962},{"date":"09-04-2020","hospitalizations":13909,"death":24473},{"date":"09-05-2020","hospitalizations":13076,"death":24958},{"date":"09-06-2020","hospitalizations":12271,"death":25416},{"date":"09-07-2020","hospitalizations":11496,"death":25848},{"date":"09-08-2020","hospitalizations":10753,"death":26254},{"date":"09-09-2020","hospitalizations":10046,"death":26637},{"date":"09-10-2020","hospitalizations":9372,"death":26997},{"date":"09-11-2020","hospitalizations":8735,"death":27334},{"date":"09-12-2020","hospitalizations":8132,"death":27650},{"date":"09-13-2020","hospitalizations":7565,"death":27946},{"date":"09-14-2020","hospitalizations":7032,"death":28222},{"date":"09-15-2020","hospitalizations":6531,"death":28481},{"date":"09-16-2020","hospitalizations":6064,"death":28723},{"date":"09-17-2020","hospitalizations":5627,"death":28948},{"date":"09-18-2020","hospitalizations":5218,"death":29159},{"date":"09-19-2020","hospitalizations":4838,"death":29355},{"date":"09-20-2020","hospitalizations":4484,"death":29538},{"date":"09-21-2020","hospitalizations":4155,"death":29709},{"date":"09-22-2020","hospitalizations":3850,"death":29868},{"date":"09-23-2020","hospitalizations":3566,"death":30016},{"date":"09-24-2020","hospitalizations":3303,"death":30154},{"date":"09-25-2020","hospitalizations":3061,"death":30282},{"date":"09-26-2020","hospitalizations":2836,"death":30401},{"date":"09-27-2020","hospitalizations":2628,"death":30512},{"date":"09-28-2020","hospitalizations":2436,"death":30616}]