[{"date":"03-09-2020","hospitalizations":0,"death":0},{"date":"03-10-2020","hospitalizations":0,"death":0},{"date":"03-11-2020","hospitalizations":0,"death":0},{"date":"03-12-2020","hospitalizations":0,"death":0},{"date":"03-13-2020","hospitalizations":0,"death":0},{"date":"03-14-2020","hospitalizations":0,"death":0},{"date":"03-15-2020","hospitalizations":0,"death":0},{"date":"03-16-2020","hospitalizations":0,"death":0},{"date":"03-17-2020","hospitalizations":1,"death":0},{"date":"03-18-2020","hospitalizations":1,"death":0},{"date":"03-19-2020","hospitalizations":2,"death":0},{"date":"03-20-2020","hospitalizations":3,"death":0},{"date":"03-21-2020","hospitalizations":4,"death":0},{"date":"03-22-2020","hospitalizations":5,"death":0},{"date":"03-23-2020","hospitalizations":7,"death":0},{"date":"03-24-2020","hospitalizations":10,"death":0},{"date":"03-25-2020","hospitalizations":13,"death":0},{"date":"03-26-2020","hospitalizations":18,"death":0},{"date":"03-27-2020","hospitalizations":23,"death":0},{"date":"03-28-2020","hospitalizations":30,"death":0},{"date":"03-29-2020","hospitalizations":38,"death":0},{"date":"03-30-2020","hospitalizations":48,"death":0},{"date":"03-31-2020","hospitalizations":58,"death":0},{"date":"04-01-2020","hospitalizations":70,"death":0},{"date":"04-02-2020","hospitalizations":83,"death":0},{"date":"04-03-2020","hospitalizations":97,"death":0},{"date":"04-04-2020","hospitalizations":110,"death":0},{"date":"04-05-2020","hospitalizations":123,"death":0},{"date":"04-06-2020","hospitalizations":136,"death":0},{"date":"04-07-2020","hospitalizations":146,"death":0},{"date":"04-08-2020","hospitalizations":156,"death":0},{"date":"04-09-2020","hospitalizations":164,"death":0},{"date":"04-10-2020","hospitalizations":171,"death":0},{"date":"04-11-2020","hospitalizations":176,"death":0},{"date":"04-12-2020","hospitalizations":181,"death":0},{"date":"04-13-2020","hospitalizations":184,"death":0},{"date":"04-14-2020","hospitalizations":187,"death":0},{"date":"04-15-2020","hospitalizations":189,"death":0},{"date":"04-16-2020","hospitalizations":191,"death":0},{"date":"04-17-2020","hospitalizations":192,"death":0},{"date":"04-18-2020","hospitalizations":193,"death":0},{"date":"04-19-2020","hospitalizations":193,"death":0},{"date":"04-20-2020","hospitalizations":193,"death":0},{"date":"04-21-2020","hospitalizations":192,"death":0},{"date":"04-22-2020","hospitalizations":191,"death":0},{"date":"04-23-2020","hospitalizations":190,"death":2},{"date":"04-24-2020","hospitalizations":189,"death":9},{"date":"04-25-2020","hospitalizations":188,"death":17},{"date":"04-26-2020","hospitalizations":186,"death":24},{"date":"04-27-2020","hospitalizations":185,"death":31},{"date":"04-28-2020","hospitalizations":183,"death":38},{"date":"04-29-2020","hospitalizations":181,"death":46},{"date":"04-30-2020","hospitalizations":180,"death":53},{"date":"05-01-2020","hospitalizations":178,"death":60},{"date":"05-02-2020","hospitalizations":176,"death":67},{"date":"05-03-2020","hospitalizations":174,"death":74},{"date":"05-04-2020","hospitalizations":172,"death":80},{"date":"05-05-2020","hospitalizations":170,"death":87},{"date":"05-06-2020","hospitalizations":168,"death":94},{"date":"05-07-2020","hospitalizations":166,"death":101},{"date":"05-08-2020","hospitalizations":163,"death":107},{"date":"05-09-2020","hospitalizations":161,"death":114},{"date":"05-10-2020","hospitalizations":159,"death":120},{"date":"05-11-2020","hospitalizations":157,"death":126},{"date":"05-12-2020","hospitalizations":155,"death":133},{"date":"05-13-2020","hospitalizations":153,"death":139},{"date":"05-14-2020","hospitalizations":151,"death":145},{"date":"05-15-2020","hospitalizations":149,"death":151},{"date":"05-16-2020","hospitalizations":147,"death":157},{"date":"05-17-2020","hospitalizations":145,"death":163},{"date":"05-18-2020","hospitalizations":143,"death":168},{"date":"05-19-2020","hospitalizations":141,"death":174},{"date":"05-20-2020","hospitalizations":139,"death":180},{"date":"05-21-2020","hospitalizations":137,"death":185},{"date":"05-22-2020","hospitalizations":135,"death":191},{"date":"05-23-2020","hospitalizations":133,"death":196},{"date":"05-24-2020","hospitalizations":131,"death":201},{"date":"05-25-2020","hospitalizations":129,"death":207},{"date":"05-26-2020","hospitalizations":127,"death":212},{"date":"05-27-2020","hospitalizations":126,"death":217},{"date":"05-28-2020","hospitalizations":124,"death":222},{"date":"05-29-2020","hospitalizations":122,"death":227},{"date":"05-30-2020","hospitalizations":120,"death":232},{"date":"05-31-2020","hospitalizations":118,"death":236},{"date":"06-01-2020","hospitalizations":117,"death":241},{"date":"06-02-2020","hospitalizations":115,"death":246},{"date":"06-03-2020","hospitalizations":113,"death":250},{"date":"06-04-2020","hospitalizations":112,"death":255},{"date":"06-05-2020","hospitalizations":111,"death":259},{"date":"06-06-2020","hospitalizations":110,"death":264},{"date":"06-07-2020","hospitalizations":110,"death":268},{"date":"06-08-2020","hospitalizations":111,"death":273},{"date":"06-09-2020","hospitalizations":112,"death":277},{"date":"06-10-2020","hospitalizations":113,"death":282},{"date":"06-11-2020","hospitalizations":116,"death":286},{"date":"06-12-2020","hospitalizations":119,"death":291},{"date":"06-13-2020","hospitalizations":123,"death":296},{"date":"06-14-2020","hospitalizations":129,"death":301},{"date":"06-15-2020","hospitalizations":135,"death":306},{"date":"06-16-2020","hospitalizations":143,"death":311},{"date":"06-17-2020","hospitalizations":153,"death":317},{"date":"06-18-2020","hospitalizations":164,"death":323},{"date":"06-19-2020","hospitalizations":177,"death":330},{"date":"06-20-2020","hospitalizations":192,"death":337},{"date":"06-21-2020","hospitalizations":208,"death":344},{"date":"06-22-2020","hospitalizations":227,"death":353},{"date":"06-23-2020","hospitalizations":248,"death":362},{"date":"06-24-2020","hospitalizations":271,"death":372},{"date":"06-25-2020","hospitalizations":296,"death":382},{"date":"06-26-2020","hospitalizations":324,"death":394},{"date":"06-27-2020","hospitalizations":355,"death":407},{"date":"06-28-2020","hospitalizations":389,"death":421},{"date":"06-29-2020","hospitalizations":427,"death":436},{"date":"06-30-2020","hospitalizations":467,"death":453},{"date":"07-01-2020","hospitalizations":511,"death":471},{"date":"07-02-2020","hospitalizations":558,"death":491},{"date":"07-03-2020","hospitalizations":608,"death":513},{"date":"07-04-2020","hospitalizations":663,"death":537},{"date":"07-05-2020","hospitalizations":720,"death":562},{"date":"07-06-2020","hospitalizations":782,"death":590},{"date":"07-07-2020","hospitalizations":851,"death":627},{"date":"07-08-2020","hospitalizations":925,"death":670},{"date":"07-09-2020","hospitalizations":1003,"death":716},{"date":"07-10-2020","hospitalizations":1084,"death":767},{"date":"07-11-2020","hospitalizations":1169,"death":821},{"date":"07-12-2020","hospitalizations":1258,"death":880},{"date":"07-13-2020","hospitalizations":1350,"death":943},{"date":"07-14-2020","hospitalizations":1445,"death":1011},{"date":"07-15-2020","hospitalizations":1545,"death":1083},{"date":"07-16-2020","hospitalizations":1647,"death":1161},{"date":"07-17-2020","hospitalizations":1754,"death":1244},{"date":"07-18-2020","hospitalizations":1864,"death":1332},{"date":"07-19-2020","hospitalizations":1977,"death":1426},{"date":"07-20-2020","hospitalizations":2093,"death":1526},{"date":"07-21-2020","hospitalizations":2212,"death":1631},{"date":"07-22-2020","hospitalizations":2333,"death":1743},{"date":"07-23-2020","hospitalizations":2457,"death":1861},{"date":"07-24-2020","hospitalizations":2582,"death":1984},{"date":"07-25-2020","hospitalizations":2709,"death":2115},{"date":"07-26-2020","hospitalizations":2836,"death":2251},{"date":"07-27-2020","hospitalizations":2964,"death":2394},{"date":"07-28-2020","hospitalizations":3091,"death":2544},{"date":"07-29-2020","hospitalizations":3217,"death":2700},{"date":"07-30-2020","hospitalizations":3341,"death":2862},{"date":"07-31-2020","hospitalizations":3462,"death":3031},{"date":"08-01-2020","hospitalizations":3580,"death":3205},{"date":"08-02-2020","hospitalizations":3695,"death":3386},{"date":"08-03-2020","hospitalizations":3804,"death":3573},{"date":"08-04-2020","hospitalizations":3908,"death":3765},{"date":"08-05-2020","hospitalizations":4006,"death":3962},{"date":"08-06-2020","hospitalizations":4096,"death":4165},{"date":"08-07-2020","hospitalizations":4179,"death":4372},{"date":"08-08-2020","hospitalizations":4254,"death":4583},{"date":"08-09-2020","hospitalizations":4320,"death":4798},{"date":"08-10-2020","hospitalizations":4377,"death":5017},{"date":"08-11-2020","hospitalizations":4425,"death":5239},{"date":"08-12-2020","hospitalizations":4463,"death":5463},{"date":"08-13-2020","hospitalizations":4491,"death":5690},{"date":"08-14-2020","hospitalizations":4509,"death":5918},{"date":"08-15-2020","hospitalizations":4517,"death":6147},{"date":"08-16-2020","hospitalizations":4516,"death":6377},{"date":"08-17-2020","hospitalizations":4504,"death":6606},{"date":"08-18-2020","hospitalizations":4483,"death":6836},{"date":"08-19-2020","hospitalizations":4453,"death":7064},{"date":"08-20-2020","hospitalizations":4414,"death":7292},{"date":"08-21-2020","hospitalizations":4367,"death":7517},{"date":"08-22-2020","hospitalizations":4311,"death":7741},{"date":"08-23-2020","hospitalizations":4249,"death":7962},{"date":"08-24-2020","hospitalizations":4178,"death":8180},{"date":"08-25-2020","hospitalizations":4103,"death":8395},{"date":"08-26-2020","hospitalizations":4022,"death":8606},{"date":"08-27-2020","hospitalizations":3935,"death":8814},{"date":"08-28-2020","hospitalizations":3844,"death":9017},{"date":"08-29-2020","hospitalizations":3748,"death":9216},{"date":"08-30-2020","hospitalizations":3650,"death":9411},{"date":"08-31-2020","hospitalizations":3549,"death":9600},{"date":"09-01-2020","hospitalizations":3445,"death":9785},{"date":"09-02-2020","hospitalizations":3340,"death":9965},{"date":"09-03-2020","hospitalizations":3234,"death":10139},{"date":"09-04-2020","hospitalizations":3128,"death":10309},{"date":"09-05-2020","hospitalizations":3021,"death":10473},{"date":"09-06-2020","hospitalizations":2915,"death":10632},{"date":"09-07-2020","hospitalizations":2809,"death":10785},{"date":"09-08-2020","hospitalizations":2704,"death":10933},{"date":"09-09-2020","hospitalizations":2600,"death":11076},{"date":"09-10-2020","hospitalizations":2498,"death":11214},{"date":"09-11-2020","hospitalizations":2397,"death":11347},{"date":"09-12-2020","hospitalizations":2299,"death":11475},{"date":"09-13-2020","hospitalizations":2202,"death":11597},{"date":"09-14-2020","hospitalizations":2108,"death":11715},{"date":"09-15-2020","hospitalizations":2017,"death":11828},{"date":"09-16-2020","hospitalizations":1927,"death":11936},{"date":"09-17-2020","hospitalizations":1841,"death":12040},{"date":"09-18-2020","hospitalizations":1757,"death":12139},{"date":"09-19-2020","hospitalizations":1676,"death":12234},{"date":"09-20-2020","hospitalizations":1598,"death":12325},{"date":"09-21-2020","hospitalizations":1523,"death":12412},{"date":"09-22-2020","hospitalizations":1450,"death":12495},{"date":"09-23-2020","hospitalizations":1380,"death":12574}]